benchtmpl/__init__.py
benchtmpl/error.py
benchtmpl/backend/__init__.py
benchtmpl/backend/base.py
benchtmpl/backend/files.py
benchtmpl/backend/util.py
benchtmpl/io/__init__.py
benchtmpl/io/scanner.py
benchtmpl/io/files/__init__.py
benchtmpl/io/files/base.py
benchtmpl/io/files/store.py
benchtmpl/util/__init__.py
benchtmpl/util/core.py
benchtmpl/util/tests.py
benchtmpl/workflow/__init__.py
benchtmpl/workflow/state.py
benchtmpl/workflow/benchmark/__init__.py
benchtmpl/workflow/benchmark/base.py
benchtmpl/workflow/benchmark/loader.py
benchtmpl/workflow/benchmark/schema.py
benchtmpl/workflow/parameter/__init__.py
benchtmpl/workflow/parameter/base.py
benchtmpl/workflow/parameter/declaration.py
benchtmpl/workflow/parameter/util.py
benchtmpl/workflow/parameter/value.py
benchtmpl/workflow/resource/__init__.py
benchtmpl/workflow/resource/base.py
benchtmpl/workflow/template/__init__.py
benchtmpl/workflow/template/base.py
benchtmpl/workflow/template/loader.py
benchtmpl/workflow/template/repo.py
benchtmpl/workflow/template/util.py
benchmark_templates-0.1.2.dist-info/LICENSE
benchmark_templates-0.1.2.dist-info/METADATA
benchmark_templates-0.1.2.dist-info/WHEEL
benchmark_templates-0.1.2.dist-info/top_level.txt
benchmark_templates-0.1.2.dist-info/RECORD
