Metadata-Version: 2.1
Name: benchmark-templates
Version: 0.1.2
Summary: Workflow Templates for Reproducible Data Analysis Benchmarks
Home-page: https://github.com/scailfin/benchmark-templates
Author: Heiko Mueller
Author-email: heiko.muller@gmail.com
License: MIT
Keywords: reproducibility benchmarks data analysis
Platform: UNKNOWN
Classifier: License :: OSI Approved :: MIT License
Classifier: Operating System :: OS Independent
Classifier: Programming Language :: Python :: 2
Classifier: Programming Language :: Python :: 2.7
Classifier: Programming Language :: Python :: 3
Classifier: Programming Language :: Python :: 3.6
Classifier: Programming Language :: Python :: 3.7
Classifier: Programming Language :: Python
Requires-Dist: future
Requires-Dist: gitpython
Requires-Dist: jsonschema
Requires-Dist: pyyaml (>=5.1)
Provides-Extra: docs
Requires-Dist: Sphinx ; extra == 'docs'
Requires-Dist: sphinx-rtd-theme ; extra == 'docs'
Provides-Extra: tests
Requires-Dist: coverage (>=4.0) ; extra == 'tests'
Requires-Dist: pytest ; extra == 'tests'
Requires-Dist: pytest-cov ; extra == 'tests'
Requires-Dist: tox ; extra == 'tests'
